pyargman.py
pyargman-0.0.4.dist-info/licenses/LICENSE
pyargman-0.0.4.dist-info/METADATA
pyargman-0.0.4.dist-info/WHEEL
pyargman-0.0.4.dist-info/top_level.txt
pyargman-0.0.4.dist-info/RECORD
