Metadata-Version: 2.4
Name: pyargman
Version: 0.0.4
Summary: A Python module like argumentparser for managing comandline  arguments,
Author-email: keralaboy <keralaboypypi@keralaboy.anonaddy.com>
License-Expression: MIT
Project-URL: Homepage, https://github.com/its-me-abi/pyargman
Keywords: cli,arguments,manager,alternative
Classifier: Development Status :: 4 - Beta
Classifier: Programming Language :: Python
Requires-Python: >=3.6
License-File: LICENSE
Dynamic: license-file
